nti/__init__.py
nti/traversal/__init__.py
nti/traversal/compat.py
nti/traversal/configure.zcml
nti/traversal/location.py
nti/traversal/traversal.py
nti/traversal/tests/__init__.py
nti/traversal/tests/test_compat.py
nti/traversal/tests/test_location.py
nti/traversal/tests/test_traversal.py
nti_traversal-1.1.0.dist-info/licenses/AUTHORS
nti_traversal-1.1.0.dist-info/licenses/LICENSE
nti_traversal-1.1.0.dist-info/METADATA
nti_traversal-1.1.0.dist-info/WHEEL
nti_traversal-1.1.0.dist-info/top_level.txt
nti_traversal-1.1.0.dist-info/zip-safe
nti_traversal-1.1.0.dist-info/RECORD
